<root annotationID="0" passageID="2922_0">
  <attributes />
  <extra format="ucca" />
  <layer layerID="0">
    <attributes />
    <extra doc="[[[11935558616188258213, 17682826258315136684, 164681854541413346, 86, 0, 2, 400, 5, 16072095006890171862, 9350754067018752509, 16203534885047373824], [2593208677638477497, 2593208677638477497, 2593208677638477497, 97, 0, 2, 445, 4, 2593208677638477497, 2593208677638477497, 2593208677638477497], [830457246522405261, 830457246522405261, 10554686591937588953, 84, 0, 2, 402, 1, 13110060611322374290, 15817570140490810055, 16957618830852774490], [12400684381872086361, 4473158105997569131, 783433942507015291, 92, 0, 2, 429, 2, 13110060611322374290, 8861071527689086543, 7880491877800203539], [14692702688101715474, 14692702688101715474, 9188597074677201817, 100, 0, 2, 405, 1, 13110060611322374290, 15817570140490810055, 13891979019686982531], [12558846041070486771, 12558846041070486771, 3822385049556375858, 100, 0, 2, 8206900633647566924, 0, 13110060611322374290, 15598372446745583797, 16679871905258096564], [14857327008534041041, 14857327008534041041, 10554686591937588953, 84, 0, 2, 398, -1, 13110060611322374290, 8861071527689086543, 12182527387764416033], [12646065887601541794, 12646065887601541794, 12646065887601541794, 97, 0, 2, 445, -2, 12646065887601541794, 12646065887601541794, 12646065887601541794]]]" />
    <node ID="0.1" type="Word">
      <attributes paragraph="1" paragraph_position="1" text="However" />
    </node>
    <node ID="0.2" type="Punctuation">
      <attributes paragraph="1" paragraph_position="2" text="," />
    </node>
    <node ID="0.3" type="Word">
      <attributes paragraph="1" paragraph_position="3" text="hidden" />
    </node>
    <node ID="0.4" type="Word">
      <attributes paragraph="1" paragraph_position="4" text="problems" />
    </node>
    <node ID="0.5" type="Word">
      <attributes paragraph="1" paragraph_position="5" text="have" />
    </node>
    <node ID="0.6" type="Word">
      <attributes paragraph="1" paragraph_position="6" text="become" />
    </node>
    <node ID="0.7" type="Word">
      <attributes paragraph="1" paragraph_position="7" text="prominent" />
    </node>
    <node ID="0.8" type="Punctuation">
      <attributes paragraph="1" paragraph_position="8" text="." />
    </node>
  </layer>
  <layer layerID="1">
    <attributes />
    <node ID="1.1" type="FN">
      <attributes />
      <edge toID="1.2" type="L">
        <attributes />
        <category tag="L" />
      </edge>
      <edge toID="1.3" type="U">
        <attributes />
        <category tag="U" />
      </edge>
      <edge toID="1.4" type="H">
        <attributes />
        <category tag="H" />
      </edge>
    </node>
    <node ID="1.2" type="FN">
      <attributes />
      <edge toID="0.1" type="Terminal">
        <attributes />
        <category tag="Terminal" />
      </edge>
    </node>
    <node ID="1.3" type="PNCT">
      <attributes />
      <edge toID="0.2" type="Terminal">
        <attributes />
        <category tag="Terminal" />
      </edge>
    </node>
    <node ID="1.4" type="FN">
      <attributes />
      <edge toID="1.5" type="A">
        <attributes />
        <category tag="A" />
      </edge>
      <edge toID="1.6" type="F">
        <attributes />
        <category tag="F" />
      </edge>
      <edge toID="1.7" type="D">
        <attributes />
        <category tag="D" />
      </edge>
      <edge toID="1.8" type="A">
        <attributes />
        <category tag="A" />
      </edge>
      <edge toID="1.9" type="U">
        <attributes />
        <category tag="U" />
      </edge>
    </node>
    <node ID="1.5" type="FN">
      <attributes />
      <edge toID="1.10" type="E">
        <attributes />
        <category tag="E" />
      </edge>
      <edge toID="1.11" type="C">
        <attributes />
        <category tag="C" />
      </edge>
    </node>
    <node ID="1.6" type="FN">
      <attributes />
      <edge toID="0.5" type="Terminal">
        <attributes />
        <category tag="Terminal" />
      </edge>
    </node>
    <node ID="1.7" type="FN">
      <attributes />
      <edge toID="0.6" type="Terminal">
        <attributes />
        <category tag="Terminal" />
      </edge>
    </node>
    <node ID="1.8" type="FN">
      <attributes />
      <edge toID="0.7" type="Terminal">
        <attributes />
        <category tag="Terminal" />
      </edge>
    </node>
    <node ID="1.9" type="PNCT">
      <attributes />
      <edge toID="0.8" type="Terminal">
        <attributes />
        <category tag="Terminal" />
      </edge>
    </node>
    <node ID="1.10" type="FN">
      <attributes />
      <edge toID="0.3" type="Terminal">
        <attributes />
        <category tag="Terminal" />
      </edge>
    </node>
    <node ID="1.11" type="FN">
      <attributes />
      <edge toID="0.4" type="Terminal">
        <attributes />
        <category tag="Terminal" />
      </edge>
    </node>
  </layer>
</root>
