<root annotationID="0" passageID="29799_0">
  <attributes />
  <extra format="ucca" />
  <layer layerID="0">
    <attributes />
    <extra doc="[[[4690420944186131903, null, 13656873538139661788, 95, 0, 2, 429, 1, 101, 4690420944186131903, 4690420944186131903], [959164148857638496, 10382539506755952630, 9188597074677201817, 100, 0, 2, 8206900633647566924, 0, 4370460163704169311, 11901859001352538922, 959164148857638496], [2077320337565082816, 2077320337565082816, 15308085513773655218, 92, 0, 2, 7037928807040764755, 2, 13110060611322374290, 15598372446745583797, 14387080380872362826], [9153284864653046197, 9153284864653046197, 8214596291009089021, 97, 0, 2, 445, 1, 9153284864653046197, 9153284864653046197, 9153284864653046197], [16477424308483498569, 16477424308483498569, 15308085513773655218, 92, 0, 2, 440, 2, 13110060611322374290, 2985121464356781022, 3379727247772060121], [16428057658620181782, 16428057658620181782, 74, 94, 0, 2, 8110129090154140942, -1, 3155823383004454315, 11221368173670222813, 16428057658620181782], [2077320337565082816, 2077320337565082816, 15308085513773655218, 92, 0, 2, 404, -5, 13110060611322374290, 15598372446745583797, 14387080380872362826], [17494803046312582752, 17494803046312582752, 12646065887601541794, 97, 0, 2, 445, -6, 17494803046312582752, 17494803046312582752, 17494803046312582752]]]" />
    <node ID="0.1" type="Word">
      <attributes paragraph="1" paragraph_position="1" text="I" />
    </node>
    <node ID="0.2" type="Word">
      <attributes paragraph="1" paragraph_position="2" text="am" />
    </node>
    <node ID="0.3" type="Word">
      <attributes paragraph="1" paragraph_position="3" text="blood" />
    </node>
    <node ID="0.4" type="Punctuation">
      <attributes paragraph="1" paragraph_position="4" text="-" />
    </node>
    <node ID="0.5" type="Word">
      <attributes paragraph="1" paragraph_position="5" text="life" />
    </node>
    <node ID="0.6" type="Word">
      <attributes paragraph="1" paragraph_position="6" text="'s" />
    </node>
    <node ID="0.7" type="Word">
      <attributes paragraph="1" paragraph_position="7" text="blood" />
    </node>
    <node ID="0.8" type="Punctuation">
      <attributes paragraph="1" paragraph_position="8" text="!" />
    </node>
  </layer>
  <layer layerID="1">
    <attributes />
    <node ID="1.1" type="FN">
      <attributes />
      <edge toID="1.2" type="H">
        <attributes />
        <category tag="H" />
      </edge>
    </node>
    <node ID="1.2" type="FN">
      <attributes />
      <edge toID="1.3" type="A">
        <attributes />
        <category tag="A" />
      </edge>
      <edge toID="1.4" type="F">
        <attributes />
        <category tag="F" />
      </edge>
      <edge toID="1.5" type="A">
        <attributes />
        <category tag="A" />
      </edge>
      <edge toID="1.6" type="P">
        <attributes />
        <category tag="P" />
      </edge>
      <edge toID="1.7" type="U">
        <attributes />
        <category tag="U" />
      </edge>
    </node>
    <node ID="1.3" type="FN">
      <attributes />
      <edge toID="0.1" type="Terminal">
        <attributes />
        <category tag="Terminal" />
      </edge>
    </node>
    <node ID="1.4" type="FN">
      <attributes />
      <edge toID="0.2" type="Terminal">
        <attributes />
        <category tag="Terminal" />
      </edge>
    </node>
    <node ID="1.5" type="FN">
      <attributes />
      <edge toID="1.8" type="E">
        <attributes />
        <category tag="E" />
      </edge>
      <edge toID="1.9" type="R">
        <attributes />
        <category tag="R" />
      </edge>
    </node>
    <node ID="1.6" type="FN">
      <attributes />
      <edge toID="0.7" type="Terminal">
        <attributes />
        <category tag="Terminal" />
      </edge>
    </node>
    <node ID="1.7" type="PNCT">
      <attributes />
      <edge toID="0.8" type="Terminal">
        <attributes />
        <category tag="Terminal" />
      </edge>
    </node>
    <node ID="1.8" type="FN">
      <attributes />
      <edge toID="1.10" type="E">
        <attributes />
        <category tag="E" />
      </edge>
      <edge toID="1.11" type="U">
        <attributes />
        <category tag="U" />
      </edge>
      <edge toID="1.12" type="C">
        <attributes />
        <category tag="C" />
      </edge>
    </node>
    <node ID="1.9" type="FN">
      <attributes />
      <edge toID="0.6" type="Terminal">
        <attributes />
        <category tag="Terminal" />
      </edge>
    </node>
    <node ID="1.10" type="FN">
      <attributes />
      <edge toID="0.3" type="Terminal">
        <attributes />
        <category tag="Terminal" />
      </edge>
    </node>
    <node ID="1.11" type="PNCT">
      <attributes />
      <edge toID="0.4" type="Terminal">
        <attributes />
        <category tag="Terminal" />
      </edge>
    </node>
    <node ID="1.12" type="FN">
      <attributes />
      <edge toID="0.5" type="Terminal">
        <attributes />
        <category tag="Terminal" />
      </edge>
    </node>
  </layer>
</root>
