<root annotationID="0" passageID="18218_0">
  <attributes />
  <extra format="ucca" />
  <layer layerID="0">
    <attributes />
    <extra doc="[[[17217008488255594911, 5946595046901399946, 10554686591937588953, 84, 0, 2, 402, 1, 16072095006890171862, 16961793518281001049, 15480957645181813644], [7593739049417968140, 7593739049417968140, 783433942507015291, 92, 0, 2, 8206900633647566924, 0, 13110060611322374290, 8861071527689086543, 16838316573854262908], [18194338103975822726, 18194338103975822726, 1292078113972184607, 85, 0, 2, 443, -1, 13110060611322374290, 2985121464356781022, 11402152577528684049], [11220165667154648082, 11220165667154648082, 15794550382381185553, 96, 380, 3, 7037928807040764755, 1, 16072095006890171862, 18003918085672799305, 5179928102577838771], [9327004864153680235, 9327004864153680235, 15794550382381185553, 96, 380, 1, 439, -2, 16072095006890171862, 17714545831559622561, 4065608743356409431], [2593208677638477497, 2593208677638477497, 2593208677638477497, 97, 0, 2, 445, -1, 2593208677638477497, 2593208677638477497, 2593208677638477497], [7831658034963690409, 7831658034963690409, 1292078113972184607, 85, 0, 2, 443, -5, 13110060611322374290, 13110760720460257827, 16701608521236914874], [7912607190021218467, 7912607190021218467, 15794550382381185553, 96, 384, 3, 439, -1, 10887629174180191697, 16337536289976144572, 12503787410125600258], [2593208677638477497, 2593208677638477497, 2593208677638477497, 97, 0, 2, 445, -1, 2593208677638477497, 2593208677638477497, 2593208677638477497], [1286636410600250842, 1286636410600250842, 15794550382381185553, 96, 384, 3, 403, -2, 16072095006890171862, 5582244037879929967, 16869941268100621406], [12646065887601541794, 12646065887601541794, 12646065887601541794, 97, 0, 2, 445, -9, 12646065887601541794, 12646065887601541794, 12646065887601541794]]]" />
    <node ID="0.1" type="Word">
      <attributes paragraph="1" paragraph_position="1" text="tr&#7867; tu&#7893;i" />
    </node>
    <node ID="0.2" type="Word">
      <attributes paragraph="1" paragraph_position="2" text="Nh&#7919;ng ng&#432;&#7901;i" />
    </node>
    <node ID="0.3" type="Word">
      <attributes paragraph="1" paragraph_position="3" text="nh&#432;" />
    </node>
    <node ID="0.4" type="Word">
      <attributes paragraph="1" paragraph_position="4" text="Jazmin" />
    </node>
    <node ID="0.5" type="Word">
      <attributes paragraph="1" paragraph_position="5" text="Perez" />
    </node>
    <node ID="0.7" type="Word">
      <attributes paragraph="1" paragraph_position="7" text="t&#7915;" />
    </node>
    <node ID="0.8" type="Word">
      <attributes paragraph="1" paragraph_position="8" text="Roma" />
    </node>
    <node ID="0.10" type="Word">
      <attributes paragraph="1" paragraph_position="10" text="Texas" />
    </node>
    <node ID="0.11" type="Punctuation">
      <attributes paragraph="1" paragraph_position="11" text="." />
    </node>
  </layer>
  <layer layerID="1">
    <attributes />
    <node ID="1.1" type="FN">
      <attributes />
      <edge toID="1.2" type="H">
        <attributes />
        <category tag="H" />
      </edge>
    </node>
    <node ID="1.2" type="FN">
      <attributes />
      <edge toID="1.3" type="A">
        <attributes />
        <category tag="A" />
      </edge>
      <edge toID="1.5" type="A">
        <attributes />
        <category tag="A" />
      </edge>
    </node>
    <node ID="1.3" type="FN">
      <attributes />
      <edge toID="1.6" type="E">
        <attributes />
        <category tag="E" />
      </edge>
      <edge toID="1.7" type="C">
        <attributes />
        <category tag="C" />
      </edge>
      <edge toID="1.8" type="E">
        <attributes />
        <category tag="E" />
      </edge>
    </node>
    <node ID="1.5" type="FN">
      <attributes />
      <edge toID="1.9" type="R">
        <attributes />
        <category tag="R" />
      </edge>
      <edge toID="1.10" type="C">
        <attributes />
        <category tag="C" />
      </edge>
      <edge toID="1.12" type="E">
        <attributes />
        <category tag="E" />
      </edge>
      <edge toID="1.13" type="U">
        <attributes />
        <category tag="U" />
      </edge>
    </node>
    <node ID="1.6" type="FN">
      <attributes />
      <edge toID="0.1" type="Terminal">
        <attributes />
        <category tag="Terminal" />
      </edge>
    </node>
    <node ID="1.7" type="FN">
      <attributes />
      <edge toID="0.2" type="Terminal">
        <attributes />
        <category tag="Terminal" />
      </edge>
    </node>
    <node ID="1.8" type="FN">
      <attributes />
      <edge toID="1.14" type="R">
        <attributes />
        <category tag="R" />
      </edge>
      <edge toID="1.15" type="C">
        <attributes />
        <category tag="C" />
      </edge>
    </node>
    <node ID="1.9" type="FN">
      <attributes />
      <edge toID="0.7" type="Terminal">
        <attributes />
        <category tag="Terminal" />
      </edge>
    </node>
    <node ID="1.10" type="FN">
      <attributes />
      <edge toID="0.8" type="Terminal">
        <attributes />
        <category tag="Terminal" />
      </edge>
    </node>
    <node ID="1.12" type="FN">
      <attributes />
      <edge toID="0.10" type="Terminal">
        <attributes />
        <category tag="Terminal" />
      </edge>
    </node>
    <node ID="1.13" type="PNCT">
      <attributes />
      <edge toID="0.11" type="Terminal">
        <attributes />
        <category tag="Terminal" />
      </edge>
    </node>
    <node ID="1.14" type="FN">
      <attributes />
      <edge toID="0.3" type="Terminal">
        <attributes />
        <category tag="Terminal" />
      </edge>
    </node>
    <node ID="1.15" type="FN">
      <attributes />
      <edge toID="0.4" type="Terminal">
        <attributes />
        <category tag="Terminal" />
      </edge>
      <edge toID="0.5" type="Terminal">
        <attributes />
        <category tag="Terminal" />
      </edge>
    </node>
  </layer>
</root>
