<root annotationID="0" passageID="24560_0">
  <attributes />
  <extra format="ucca" />
  <layer layerID="0">
    <attributes />
    <extra doc="[[[14947529218328092544, null, 13656873538139661788, 95, 0, 2, 429, 1, 10887629174180191697, 5582244037879929967, 6375554876062815730], [17573686707662795042, 8685289367999165211, 17109001835818727656, 100, 0, 2, 8206900633647566924, 0, 13110060611322374290, 16978132545290669629, 11586757942818230145], [7425985699627899538, 7425985699627899538, 15267657372422890137, 90, 0, 2, 415, 1, 4088098365541558500, 15369245168918225700, 7425985699627899538], [6905553075311563409, 6905553075311563409, 15308085513773655218, 92, 0, 2, 429, 2, 13110060611322374290, 16900879642891266615, 13148361048351484388], [6992604926141104606, 6992604926141104606, 16235386156175103506, 100, 0, 2, 405, 1, 13110060611322374290, 260667111241363922, 17438164932492296010], [13534686644065735227, 13534686644065735227, 14200088355797579614, 100, 0, 2, 408, -4, 13110060611322374290, 646772771845179972, 12291129470069670338], [15726112966383307120, 15726112966383307120, 164681854541413346, 86, 0, 2, 400, -1, 13110060611322374290, 11901859001352538922, 6878210874361030284], [7831658034963690409, 7831658034963690409, 1292078113972184607, 85, 0, 2, 443, -1, 13110060611322374290, 13110760720460257827, 16701608521236914874], [15479733260938818482, 15479733260938818482, 15308085513773655218, 92, 0, 2, 7037928807040764755, 1, 13110060611322374290, 8861071527689086543, 2204417905868041474], [7206340754463407063, 2104994216896503478, 783433942507015291, 92, 0, 2, 439, -2, 13110060611322374290, 8861071527689086543, 2810490599860701856], [2283656566040971221, 2283656566040971221, 17571114184892886314, 89, 0, 2, 407, -5, 4088098365541558500, 11901859001352538922, 2283656566040971221], [10609121202681709909, 10609121202681709909, 164681854541413346, 86, 0, 2, 400, 2, 13110060611322374290, 5097672513440128799, 15650869774315047599], [6992604926141104606, 6992604926141104606, 16235386156175103506, 100, 0, 2, 405, 1, 13110060611322374290, 260667111241363922, 17438164932492296010], [10038440415813069799, 10038440415813069799, 14200088355797579614, 100, 0, 2, 410, -8, 13110060611322374290, 260667111241363922, 6514075241449120593], [3791531372978436496, 3791531372978436496, 5595707737748328492, 94, 0, 2, 405, 1, 4370460163704169311, 15369245168918225700, 3791531372978436496], [6502919589296598169, 6502919589296598169, 14200088355797579614, 100, 0, 2, 450, -2, 13110060611322374290, 1489474827855109852, 13147371020757508111], [1771061865486759471, 4423007098037566368, 783433942507015291, 92, 0, 2, 7037928807040764755, 1, 13110060611322374290, 1720370409040345145, 1588056499098558155], [6010474665983160334, 8054865091517299512, 783433942507015291, 92, 0, 2, 416, -2, 13110060611322374290, 16978132545290669629, 8906198441074590503], [4380130941430378203, 4380130941430378203, 17202369883303991778, 90, 0, 2, 429, 2, 13110060611322374290, 15369245168918225700, 14949295185858420483], [6635067063807956629, 6635067063807956629, 16235386156175103506, 100, 0, 2, 405, 1, 4088098365541558500, 16900879642891266615, 6635067063807956629], [5650355301591636060, 5650355301591636060, 14200088355797579614, 100, 0, 2, 447, -3, 13110060611322374290, 1720370409040345145, 10806788082624814911], [9410232112791000120, 9410232112791000120, 15308085513773655218, 92, 0, 2, 416, -1, 13110060611322374290, 1720370409040345145, 7679303661980345986], [7831658034963690409, 7831658034963690409, 1292078113972184607, 85, 0, 2, 443, -2, 13110060611322374290, 13110760720460257827, 16701608521236914874], [6645506661261177361, 8931270445620108520, 783433942507015291, 92, 0, 2, 7037928807040764755, 1, 13110060611322374290, 8148669997605808657, 17688727646682232363], [14980700777765958138, 14980700777765958138, 15308085513773655218, 92, 0, 2, 7037928807040764755, 1, 13110060611322374290, 16900879642891266615, 16111258787187009011], [3214300687175894731, 3214300687175894731, 15308085513773655218, 92, 0, 2, 439, -3, 13110060611322374290, 15817570140490810055, 5012629990875267006], [3791531372978436496, 3791531372978436496, 1292078113972184607, 85, 0, 2, 405, 1, 4370460163704169311, 15369245168918225700, 3791531372978436496], [8212201967714533330, 8212201967714533330, 15308085513773655218, 92, 0, 2, 399, -7, 13110060611322374290, 16978132545290669629, 5012629990875267006], [3791531372978436496, 3791531372978436496, 1292078113972184607, 85, 0, 2, 443, -1, 4370460163704169311, 15369245168918225700, 3791531372978436496], [15545056930122316503, 208172016153456603, 783433942507015291, 92, 0, 2, 439, -1, 13110060611322374290, 16978132545290669629, 10477575395255680452], [12646065887601541794, 12646065887601541794, 12646065887601541794, 97, 0, 2, 445, -29, 12646065887601541794, 12646065887601541794, 12646065887601541794]]]" />
    <node ID="0.1" type="Word">
      <attributes paragraph="1" paragraph_position="1" text="H&#7885;" />
    </node>
    <node ID="0.2" type="Word">
      <attributes paragraph="1" paragraph_position="2" text="cho bi&#7871;t" />
    </node>
    <node ID="0.4" type="Word">
      <attributes paragraph="1" paragraph_position="4" text="h&#227;ng" />
    </node>
    <node ID="0.5" type="Word">
      <attributes paragraph="1" paragraph_position="5" text="s&#7869;" />
    </node>
    <node ID="0.6" type="Word">
      <attributes paragraph="1" paragraph_position="6" text="v&#432;&#7907;t ra kh&#7887;i" />
    </node>
    <node ID="0.9" type="Word">
      <attributes paragraph="1" paragraph_position="9" text="ch&#237;nh" />
    </node>
    <node ID="0.10" type="Word">
      <attributes paragraph="1" paragraph_position="10" text="nh&#7919;ng s&#7843;n ph&#7849;m" />
    </node>
    <node ID="0.11" type="Word">
      <attributes paragraph="1" paragraph_position="11" text="v&#224;" />
    </node>
    <node ID="0.12" type="Word">
      <attributes paragraph="1" paragraph_position="12" text="thay th&#7871;" />
    </node>
    <node ID="0.13" type="Word">
      <attributes paragraph="1" paragraph_position="13" text="s&#7869;" />
    </node>
    <node ID="0.14" type="Word">
      <attributes paragraph="1" paragraph_position="14" text="vi&#7879;c" />
    </node>
    <node ID="0.16" type="Word">
      <attributes paragraph="1" paragraph_position="16" text="cung c&#7845;p" />
    </node>
    <node ID="0.17" type="Word">
      <attributes paragraph="1" paragraph_position="17" text="doanh nghi&#7879;p" />
    </node>
    <node ID="0.18" type="Word">
      <attributes paragraph="1" paragraph_position="18" text="c&#225;c gi&#7843;i ph&#225;p" />
    </node>
    <node ID="0.19" type="Word">
      <attributes paragraph="1" paragraph_position="19" text="m&#224;" />
    </node>
    <node ID="0.20" type="Word">
      <attributes paragraph="1" paragraph_position="20" text="c&#243; th&#7875;" />
    </node>
    <node ID="0.21" type="Word">
      <attributes paragraph="1" paragraph_position="21" text="l&#224;m g&#243;i g&#7885;n" />
    </node>
    <node ID="0.22" type="Word">
      <attributes paragraph="1" paragraph_position="22" text="m&#7885;i th&#7913;" />
    </node>
    <node ID="0.23" type="Word">
      <attributes paragraph="1" paragraph_position="23" text="t&#7915;" />
    </node>
    <node ID="0.24" type="Word">
      <attributes paragraph="1" paragraph_position="24" text="d&#7919; li&#7879;u" />
    </node>
    <node ID="0.25" type="Word">
      <attributes paragraph="1" paragraph_position="25" text="trung t&#226;m" />
    </node>
    <node ID="0.26" type="Word">
      <attributes paragraph="1" paragraph_position="26" text="ph&#7847;n c&#7913;ng" />
    </node>
    <node ID="0.27" type="Word">
      <attributes paragraph="1" paragraph_position="27" text="&#273;&#7871;n" />
    </node>
    <node ID="0.28" type="Word">
      <attributes paragraph="1" paragraph_position="28" text="ph&#7847;n m&#7873;m" />
    </node>
    <node ID="0.29" type="Word">
      <attributes paragraph="1" paragraph_position="29" text="cho" />
    </node>
    <node ID="0.30" type="Word">
      <attributes paragraph="1" paragraph_position="30" text="c&#225;c d&#7883;ch v&#7909;" />
    </node>
    <node ID="0.31" type="Punctuation">
      <attributes paragraph="1" paragraph_position="31" text="." />
    </node>
  </layer>
  <layer layerID="1">
    <attributes />
    <node ID="1.1" type="FN">
      <attributes />
      <edge toID="1.2" type="H">
        <attributes />
        <category tag="H" />
      </edge>
      <edge toID="1.3" type="P">
        <attributes />
        <category tag="P" />
      </edge>
      <edge toID="1.4" type="A">
        <attributes />
        <category tag="A" />
      </edge>
    </node>
    <node ID="1.2" type="FN">
      <attributes />
      <edge toID="1.5" type="A">
        <attributes />
        <category tag="A" />
      </edge>
      <edge toID="1.6" type="P">
        <attributes />
        <category tag="P" />
      </edge>
      <edge toID="1.7" type="A">
        <attributes />
        <category tag="A" />
      </edge>
    </node>
    <node ID="1.3" type="FN">
      <attributes />
      <edge toID="1.8" type="F">
        <attributes />
        <category tag="F" />
      </edge>
      <edge toID="1.9" type="C">
        <attributes />
        <category tag="C" />
      </edge>
    </node>
    <node ID="1.4" type="FN">
      <attributes />
      <edge toID="1.11" type="P">
        <attributes />
        <category tag="P" />
      </edge>
      <edge toID="1.12" type="A">
        <attributes />
        <category tag="A" />
      </edge>
      <edge toID="1.13" type="A">
        <attributes />
        <category tag="A" />
      </edge>
    </node>
    <node ID="1.5" type="FN">
      <attributes />
      <edge toID="0.1" type="Terminal">
        <attributes />
        <category tag="Terminal" />
      </edge>
    </node>
    <node ID="1.6" type="FN">
      <attributes />
      <edge toID="0.2" type="Terminal">
        <attributes />
        <category tag="Terminal" />
      </edge>
    </node>
    <node ID="1.7" type="FN">
      <attributes />
      <edge toID="1.14" type="H">
        <attributes />
        <category tag="H" />
      </edge>
      <edge toID="1.15" type="L">
        <attributes />
        <category tag="L" />
      </edge>
      <edge toID="1.16" type="H">
        <attributes />
        <category tag="H" />
      </edge>
    </node>
    <node ID="1.8" type="FN">
      <attributes />
      <edge toID="0.13" type="Terminal">
        <attributes />
        <category tag="Terminal" />
      </edge>
    </node>
    <node ID="1.9" type="FN">
      <attributes />
      <edge toID="0.14" type="Terminal">
        <attributes />
        <category tag="Terminal" />
      </edge>
    </node>
    <node ID="1.11" type="FN">
      <attributes />
      <edge toID="0.16" type="Terminal">
        <attributes />
        <category tag="Terminal" />
      </edge>
    </node>
    <node ID="1.12" type="FN">
      <attributes />
      <edge toID="1.17" type="E">
        <attributes />
        <category tag="E" />
      </edge>
      <edge toID="1.18" type="E">
        <attributes />
        <category tag="E" />
      </edge>
      <edge toID="1.19" type="C">
        <attributes />
        <category tag="C" />
      </edge>
    </node>
    <node ID="1.13" type="FN">
      <attributes />
      <edge toID="1.20" type="R">
        <attributes />
        <category tag="R" />
      </edge>
      <edge toID="1.21" type="C">
        <attributes />
        <category tag="C" />
      </edge>
    </node>
    <node ID="1.14" type="FN">
      <attributes />
      <edge toID="1.23" type="P">
        <attributes />
        <category tag="P" />
      </edge>
      <edge toID="1.24" type="A">
        <attributes />
        <category tag="A" />
      </edge>
    </node>
    <node ID="1.15" type="FN">
      <attributes />
      <edge toID="0.11" type="Terminal">
        <attributes />
        <category tag="Terminal" />
      </edge>
    </node>
    <node ID="1.16" type="FN">
      <attributes />
      <edge toID="1.25" type="P">
        <attributes />
        <category tag="P" />
      </edge>
    </node>
    <node ID="1.17" type="FN">
      <attributes />
      <edge toID="0.17" type="Terminal">
        <attributes />
        <category tag="Terminal" />
      </edge>
    </node>
    <node ID="1.18" type="FN">
      <attributes />
      <edge toID="1.19" type="A">
        <attributes remote="True" />
        <category tag="A" />
      </edge>
      <edge toID="1.26" type="F">
        <attributes />
        <category tag="F" />
      </edge>
      <edge toID="1.27" type="P">
        <attributes />
        <category tag="P" />
      </edge>
      <edge toID="1.28" type="A">
        <attributes />
        <category tag="A" />
      </edge>
      <edge toID="1.29" type="A">
        <attributes />
        <category tag="A" />
      </edge>
    </node>
    <node ID="1.19" type="FN">
      <attributes />
      <edge toID="0.18" type="Terminal">
        <attributes />
        <category tag="Terminal" />
      </edge>
    </node>
    <node ID="1.20" type="FN">
      <attributes />
      <edge toID="0.27" type="Terminal">
        <attributes />
        <category tag="Terminal" />
      </edge>
    </node>
    <node ID="1.21" type="FN">
      <attributes />
      <edge toID="1.30" type="P">
        <attributes />
        <category tag="P" />
      </edge>
      <edge toID="1.31" type="A">
        <attributes />
        <category tag="A" />
      </edge>
    </node>
    <node ID="1.23" type="FN">
      <attributes />
      <edge toID="1.33" type="F">
        <attributes />
        <category tag="F" />
      </edge>
      <edge toID="1.34" type="C">
        <attributes />
        <category tag="C" />
      </edge>
    </node>
    <node ID="1.24" type="FN">
      <attributes />
      <edge toID="1.36" type="E">
        <attributes />
        <category tag="E" />
      </edge>
      <edge toID="1.37" type="C">
        <attributes />
        <category tag="C" />
      </edge>
    </node>
    <node ID="1.25" type="FN">
      <attributes />
      <edge toID="0.12" type="Terminal">
        <attributes />
        <category tag="Terminal" />
      </edge>
    </node>
    <node ID="1.26" type="FN">
      <attributes />
      <edge toID="0.19" type="Terminal">
        <attributes />
        <category tag="Terminal" />
      </edge>
    </node>
    <node ID="1.27" type="FN">
      <attributes />
      <edge toID="1.38" type="F">
        <attributes />
        <category tag="F" />
      </edge>
      <edge toID="1.39" type="C">
        <attributes />
        <category tag="C" />
      </edge>
    </node>
    <node ID="1.28" type="FN">
      <attributes />
      <edge toID="0.22" type="Terminal">
        <attributes />
        <category tag="Terminal" />
      </edge>
    </node>
    <node ID="1.29" type="FN">
      <attributes />
      <edge toID="1.40" type="R">
        <attributes />
        <category tag="R" />
      </edge>
      <edge toID="1.41" type="E">
        <attributes />
        <category tag="E" />
      </edge>
      <edge toID="1.42" type="C">
        <attributes />
        <category tag="C" />
      </edge>
    </node>
    <node ID="1.30" type="FN">
      <attributes />
      <edge toID="0.28" type="Terminal">
        <attributes />
        <category tag="Terminal" />
      </edge>
    </node>
    <node ID="1.31" type="FN">
      <attributes />
      <edge toID="1.43" type="R">
        <attributes />
        <category tag="R" />
      </edge>
      <edge toID="1.44" type="C">
        <attributes />
        <category tag="C" />
      </edge>
      <edge toID="1.45" type="U">
        <attributes />
        <category tag="U" />
      </edge>
    </node>
    <node ID="1.33" type="FN">
      <attributes />
      <edge toID="0.5" type="Terminal">
        <attributes />
        <category tag="Terminal" />
      </edge>
    </node>
    <node ID="1.34" type="FN">
      <attributes />
      <edge toID="0.6" type="Terminal">
        <attributes />
        <category tag="Terminal" />
      </edge>
    </node>
    <node ID="1.36" type="FN">
      <attributes />
      <edge toID="0.9" type="Terminal">
        <attributes />
        <category tag="Terminal" />
      </edge>
    </node>
    <node ID="1.37" type="FN">
      <attributes />
      <edge toID="0.10" type="Terminal">
        <attributes />
        <category tag="Terminal" />
      </edge>
    </node>
    <node ID="1.38" type="FN">
      <attributes />
      <edge toID="0.20" type="Terminal">
        <attributes />
        <category tag="Terminal" />
      </edge>
    </node>
    <node ID="1.39" type="FN">
      <attributes />
      <edge toID="0.21" type="Terminal">
        <attributes />
        <category tag="Terminal" />
      </edge>
    </node>
    <node ID="1.40" type="FN">
      <attributes />
      <edge toID="0.23" type="Terminal">
        <attributes />
        <category tag="Terminal" />
      </edge>
    </node>
    <node ID="1.41" type="FN">
      <attributes />
      <edge toID="1.46" type="E">
        <attributes />
        <category tag="E" />
      </edge>
      <edge toID="1.47" type="C">
        <attributes />
        <category tag="C" />
      </edge>
    </node>
    <node ID="1.42" type="FN">
      <attributes />
      <edge toID="0.26" type="Terminal">
        <attributes />
        <category tag="Terminal" />
      </edge>
    </node>
    <node ID="1.43" type="FN">
      <attributes />
      <edge toID="0.29" type="Terminal">
        <attributes />
        <category tag="Terminal" />
      </edge>
    </node>
    <node ID="1.44" type="FN">
      <attributes />
      <edge toID="0.30" type="Terminal">
        <attributes />
        <category tag="Terminal" />
      </edge>
    </node>
    <node ID="1.45" type="PNCT">
      <attributes />
      <edge toID="0.31" type="Terminal">
        <attributes />
        <category tag="Terminal" />
      </edge>
    </node>
    <node ID="1.46" type="FN">
      <attributes />
      <edge toID="0.24" type="Terminal">
        <attributes />
        <category tag="Terminal" />
      </edge>
    </node>
    <node ID="1.47" type="FN">
      <attributes />
      <edge toID="0.25" type="Terminal">
        <attributes />
        <category tag="Terminal" />
      </edge>
    </node>
  </layer>
</root>
