<root annotationID="0" passageID="28591_0">
  <attributes />
  <extra format="ucca" />
  <layer layerID="0">
    <attributes />
    <extra doc="[[[6909594316259897223, 6909594316259897223, 15794550382381185553, 96, 380, 3, 7037928807040764755, 2, 16072095006890171862, 16337536289976144572, 684745465822051461], [9709023768673339208, 9709023768673339208, 15794550382381185553, 96, 380, 1, 7037928807040764755, 1, 12204527652707022206, 3929483993944067416, 9709023768673339208], [17207613512316759405, 17207613512316759405, 15794550382381185553, 96, 380, 1, 8206900633647566924, 0, 16072095006890171862, 10926178514336144719, 3816247928076225467], [2593208677638477497, 2593208677638477497, 2593208677638477497, 97, 0, 2, 445, -1, 2593208677638477497, 2593208677638477497, 2593208677638477497], [7425985699627899538, 7425985699627899538, 15267657372422890137, 90, 0, 2, 415, 3, 4088098365541558500, 15369245168918225700, 7425985699627899538], [8881679497796027013, 8881679497796027013, 10554686591937588953, 84, 0, 2, 402, 2, 13110060611322374290, 6217145520856553898, 9837207709914848172], [13668224129017215276, 8409977920640963855, 10554686591937588953, 84, 381, 3, 402, 1, 16072095006890171862, 14862748245026736845, 11197236520932772837], [5220280467448633026, 5220280467448633026, 15308085513773655218, 92, 0, 2, 403, -5, 13110060611322374290, 6217145520856553898, 13147371020757508111], [12646065887601541794, 12646065887601541794, 12646065887601541794, 97, 0, 2, 445, -6, 12646065887601541794, 12646065887601541794, 12646065887601541794]]]" />
    <node ID="0.1" type="Word">
      <attributes paragraph="1" paragraph_position="1" text="Robert" />
    </node>
    <node ID="0.2" type="Word">
      <attributes paragraph="1" paragraph_position="2" text="De" />
    </node>
    <node ID="0.3" type="Word">
      <attributes paragraph="1" paragraph_position="3" text="Vincenzo" />
    </node>
    <node ID="0.6" type="Word">
      <attributes paragraph="1" paragraph_position="6" text="xu&#7845;t s&#7855;c" />
    </node>
    <node ID="0.7" type="Word">
      <attributes paragraph="1" paragraph_position="7" text="&#193;c-hen-ti-na" />
    </node>
    <node ID="0.8" type="Word">
      <attributes paragraph="1" paragraph_position="8" text="v&#7853;n &#273;&#7897;ng vi&#234;n &#273;&#225;nh g&#244;n" />
    </node>
    <node ID="0.9" type="Punctuation">
      <attributes paragraph="1" paragraph_position="9" text="." />
    </node>
  </layer>
  <layer layerID="1">
    <attributes />
    <node ID="1.1" type="FN">
      <attributes />
      <edge toID="1.2" type="H">
        <attributes />
        <category tag="H" />
      </edge>
      <edge toID="1.4" type="E">
        <attributes />
        <category tag="E" />
      </edge>
      <edge toID="1.5" type="E">
        <attributes />
        <category tag="E" />
      </edge>
      <edge toID="1.6" type="C">
        <attributes />
        <category tag="C" />
      </edge>
      <edge toID="1.7" type="U">
        <attributes />
        <category tag="U" />
      </edge>
    </node>
    <node ID="1.2" type="FN">
      <attributes />
      <edge toID="1.8" type="A">
        <attributes />
        <category tag="A" />
      </edge>
    </node>
    <node ID="1.4" type="FN">
      <attributes />
      <edge toID="0.6" type="Terminal">
        <attributes />
        <category tag="Terminal" />
      </edge>
    </node>
    <node ID="1.5" type="FN">
      <attributes />
      <edge toID="0.7" type="Terminal">
        <attributes />
        <category tag="Terminal" />
      </edge>
    </node>
    <node ID="1.6" type="FN">
      <attributes />
      <edge toID="0.8" type="Terminal">
        <attributes />
        <category tag="Terminal" />
      </edge>
    </node>
    <node ID="1.7" type="PNCT">
      <attributes />
      <edge toID="0.9" type="Terminal">
        <attributes />
        <category tag="Terminal" />
      </edge>
    </node>
    <node ID="1.8" type="FN">
      <attributes />
      <edge toID="1.9" type="C">
        <attributes />
        <category tag="C" />
      </edge>
    </node>
    <node ID="1.9" type="FN">
      <attributes />
      <edge toID="0.1" type="Terminal">
        <attributes />
        <category tag="Terminal" />
      </edge>
      <edge toID="0.2" type="Terminal">
        <attributes />
        <category tag="Terminal" />
      </edge>
      <edge toID="0.3" type="Terminal">
        <attributes />
        <category tag="Terminal" />
      </edge>
    </node>
  </layer>
</root>
