<root annotationID="0" passageID="36664_0">
  <attributes />
  <extra format="ucca" />
  <layer layerID="0">
    <attributes />
    <extra doc="[[[1435477247894870482, 9232265920510186555, 783433942507015291, 92, 0, 2, 429, 2, 785924583524300502, 9391737413944127320, 12856644686425764130], [6635067063807956629, 6635067063807956629, 16235386156175103506, 100, 0, 2, 405, 1, 4088098365541558500, 16900879642891266615, 6635067063807956629], [10382539506755952630, 10382539506755952630, 14200088355797579614, 100, 0, 2, 8206900633647566924, 0, 4370460163704169311, 15598372446745583797, 10382539506755952630], [7233594561167080607, 7233594561167080607, 10554686591937588953, 84, 0, 2, 398, -1, 13110060611322374290, 12247454108283186160, 17094567523389501479], [2283656566040971221, 2283656566040971221, 17571114184892886314, 89, 0, 2, 407, -1, 4088098365541558500, 11901859001352538922, 2283656566040971221], [12944059472034829533, 12944059472034829533, 10554686591937588953, 84, 0, 2, 410, -2, 13110060611322374290, 16978132545290669629, 9031241580089672231], [3791531372978436496, 3791531372978436496, 1292078113972184607, 85, 0, 2, 443, -1, 4370460163704169311, 15369245168918225700, 3791531372978436496], [2891606786648131804, 12240597187821890630, 783433942507015291, 92, 0, 2, 439, -1, 13110060611322374290, 15917291556903334389, 17051212862104794208], [2593208677638477497, 2593208677638477497, 2593208677638477497, 97, 0, 2, 445, -6, 2593208677638477497, 2593208677638477497, 2593208677638477497], [14560795576765492085, 14560795576765492085, 17571114184892886314, 89, 0, 2, 407, -7, 4088098365541558500, 15598372446745583797, 14560795576765492085], [5012629990875267006, 10382539506755952630, 9188597074677201817, 100, 0, 2, 410, -8, 4088098365541558500, 11901859001352538922, 5012629990875267006], [2043519015752540944, 2043519015752540944, 164681854541413346, 86, 0, 2, 425, -1, 15075103628056407474, 13210364986222294696, 2043519015752540944], [15226876150295704304, 15226876150295704304, 164681854541413346, 86, 0, 2, 400, -2, 13110060611322374290, 12247454108283186160, 12215235795949914907], [3688728440189570542, 3688728440189570542, 10554686591937588953, 84, 0, 2, 398, -3, 13110060611322374290, 8861071527689086543, 6901033109670990563], [12646065887601541794, 12646065887601541794, 12646065887601541794, 97, 0, 2, 445, -12, 12646065887601541794, 12646065887601541794, 12646065887601541794]]]" />
    <node ID="0.1" type="Word">
      <attributes paragraph="1" paragraph_position="1" text="EMG" />
    </node>
    <node ID="0.2" type="Word">
      <attributes paragraph="1" paragraph_position="2" text="c&#243; th&#7875;" />
    </node>
    <node ID="0.4" type="Word">
      <attributes paragraph="1" paragraph_position="4" text="th&#7845;y kh&#243; ch&#7883;u" />
    </node>
    <node ID="0.5" type="Word">
      <attributes paragraph="1" paragraph_position="5" text="v&#224;" />
    </node>
    <node ID="0.6" type="Word">
      <attributes paragraph="1" paragraph_position="6" text="s&#7907; h&#227;i" />
    </node>
    <node ID="0.8" type="Word">
      <attributes paragraph="1" paragraph_position="8" text="tr&#7867;" />
    </node>
    <node ID="0.10" type="Word">
      <attributes paragraph="1" paragraph_position="10" text="nh&#432;ng" />
    </node>
    <node ID="0.11" type="Word">
      <attributes paragraph="1" paragraph_position="11" text="kh&#244;ng" />
    </node>
    <node ID="0.13" type="Word">
      <attributes paragraph="1" paragraph_position="13" text="th&#432;&#7901;ng" />
    </node>
    <node ID="0.14" type="Word">
      <attributes paragraph="1" paragraph_position="14" text="g&#226;y &#273;au &#273;&#7899;n" />
    </node>
    <node ID="0.15" type="Punctuation">
      <attributes paragraph="1" paragraph_position="15" text="." />
    </node>
  </layer>
  <layer layerID="1">
    <attributes />
    <node ID="1.1" type="FN">
      <attributes />
      <edge toID="1.2" type="H">
        <attributes />
        <category tag="H" />
      </edge>
      <edge toID="1.4" type="L">
        <attributes />
        <category tag="L" />
      </edge>
      <edge toID="1.5" type="H">
        <attributes />
        <category tag="H" />
      </edge>
    </node>
    <node ID="1.2" type="FN">
      <attributes />
      <edge toID="1.6" type="A">
        <attributes />
        <category tag="A" />
      </edge>
      <edge toID="1.7" type="D">
        <attributes />
        <category tag="D" />
      </edge>
      <edge toID="1.9" type="P">
        <attributes />
        <category tag="P" />
      </edge>
      <edge toID="1.10" type="A">
        <attributes />
        <category tag="A" />
      </edge>
    </node>
    <node ID="1.4" type="FN">
      <attributes />
      <edge toID="0.10" type="Terminal">
        <attributes />
        <category tag="Terminal" />
      </edge>
    </node>
    <node ID="1.5" type="FN">
      <attributes />
      <edge toID="1.6" type="A">
        <attributes remote="True" />
        <category tag="A" />
      </edge>
      <edge toID="1.11" type="D">
        <attributes />
        <category tag="D" />
      </edge>
      <edge toID="1.13" type="D">
        <attributes />
        <category tag="D" />
      </edge>
      <edge toID="1.14" type="S">
        <attributes />
        <category tag="S" />
      </edge>
      <edge toID="1.15" type="U">
        <attributes />
        <category tag="U" />
      </edge>
    </node>
    <node ID="1.6" type="FN">
      <attributes />
      <edge toID="0.1" type="Terminal">
        <attributes />
        <category tag="Terminal" />
      </edge>
    </node>
    <node ID="1.7" type="FN">
      <attributes />
      <edge toID="0.2" type="Terminal">
        <attributes />
        <category tag="Terminal" />
      </edge>
    </node>
    <node ID="1.9" type="FN">
      <attributes />
      <edge toID="1.16" type="C">
        <attributes />
        <category tag="C" />
      </edge>
      <edge toID="1.17" type="N">
        <attributes />
        <category tag="N" />
      </edge>
      <edge toID="1.18" type="C">
        <attributes />
        <category tag="C" />
      </edge>
    </node>
    <node ID="1.10" type="FN">
      <attributes />
      <edge toID="1.20" type="C">
        <attributes />
        <category tag="C" />
      </edge>
    </node>
    <node ID="1.11" type="FN">
      <attributes />
      <edge toID="0.11" type="Terminal">
        <attributes />
        <category tag="Terminal" />
      </edge>
    </node>
    <node ID="1.13" type="FN">
      <attributes />
      <edge toID="0.13" type="Terminal">
        <attributes />
        <category tag="Terminal" />
      </edge>
    </node>
    <node ID="1.14" type="FN">
      <attributes />
      <edge toID="0.14" type="Terminal">
        <attributes />
        <category tag="Terminal" />
      </edge>
    </node>
    <node ID="1.15" type="PNCT">
      <attributes />
      <edge toID="0.15" type="Terminal">
        <attributes />
        <category tag="Terminal" />
      </edge>
    </node>
    <node ID="1.16" type="FN">
      <attributes />
      <edge toID="0.4" type="Terminal">
        <attributes />
        <category tag="Terminal" />
      </edge>
    </node>
    <node ID="1.17" type="FN">
      <attributes />
      <edge toID="0.5" type="Terminal">
        <attributes />
        <category tag="Terminal" />
      </edge>
    </node>
    <node ID="1.18" type="FN">
      <attributes />
      <edge toID="0.6" type="Terminal">
        <attributes />
        <category tag="Terminal" />
      </edge>
    </node>
    <node ID="1.20" type="FN">
      <attributes />
      <edge toID="0.8" type="Terminal">
        <attributes />
        <category tag="Terminal" />
      </edge>
    </node>
  </layer>
</root>
